cloudfloordns/__init__.py
cloudfloordns/__main__.py
cloudfloordns/client/__init__.py
cloudfloordns/client/sync/__init__.py
cloudfloordns/client/sync/client.py
cloudfloordns/client/sync/domain.py
cloudfloordns/client/sync/groups.py
cloudfloordns/client/sync/pool.py
cloudfloordns/client/sync/record.py
cloudfloordns/client/sync/zone.py
cloudfloordns/constants.py
cloudfloordns/models/__init__.py
cloudfloordns/models/domain.py
cloudfloordns/models/groups.py
cloudfloordns/models/record.py
cloudfloordns/models/zone.py
cloudfloordns/utils/__init__.py
cloudfloordns-0.1.8.dist-info/LICENSE
cloudfloordns-0.1.8.dist-info/METADATA
cloudfloordns-0.1.8.dist-info/WHEEL
cloudfloordns-0.1.8.dist-info/RECORD
