Metadata-Version: 2.1
Name: cloudfloordns
Version: 0.1.8
Summary: 
Home-page: https://github.com/divad1196/pycloudfloordns
Author: David Gallay
Author-email: david.gallay.96@gmail.com
Requires-Python: >=3.9.0,<4.0.0
Classifier: Programming Language :: Python :: 3
Classifier: Programming Language :: Python :: 3.9
Classifier: Programming Language :: Python :: 3.10
Classifier: Programming Language :: Python :: 3.11
Classifier: Programming Language :: Python :: 3.12
Requires-Dist: gevent (>=24.2.1,<25.0.0)
Requires-Dist: pydantic (>=2.6.3,<3.0.0)
Requires-Dist: ratelimit (>=2.2.1,<3.0.0)
Requires-Dist: requests (>=2.31.0,<3.0.0)
Project-URL: Documentation, https://divad1196.github.io/pycloudfloordns
Project-URL: Repository, https://github.com/divad1196/pycloudfloordns
